Metadata-Version: 2.1
Name: wdonate
Version: 1.0.7
Summary: Это модуль для взаимодействия с API WDonate
Home-page: https://github.com/hleb2702/wdonate_python.git
Download-URL: https://github.com/hleb2702/wdonate_python/archive/refs/tags/wdonate.zip
Author: Hleb2702
Author-email: glebstetko2@gmail.com
License: Apache License, Version 2.0, see LICENSE file
Requires: requests
Requires: random
